smanim/__init__.py
smanim/bidirectional/__init__.py
smanim/bidirectional/bidirectional.py
smanim/bidirectional/custom_linecache.py
smanim/canvas.py
smanim/config.py
smanim/constants.py
smanim/mobject/geometry/__init__.py
smanim/mobject/geometry/arc.py
smanim/mobject/geometry/circle.py
smanim/mobject/geometry/line.py
smanim/mobject/geometry/polygon.py
smanim/mobject/geometry/shape_matchers.py
smanim/mobject/geometry/tips.py
smanim/mobject/graph.py
smanim/mobject/graphing/__init__.py
smanim/mobject/graphing/coordinate_systems.py
smanim/mobject/graphing/functions.py
smanim/mobject/graphing/number_line.py
smanim/mobject/graphing/scale.py
smanim/mobject/group.py
smanim/mobject/mobject.py
smanim/mobject/programming/box_list.py
smanim/mobject/svg/__init__.py
smanim/mobject/svg/brace.py
smanim/mobject/svg/lambda_char.py
smanim/mobject/svg/svg_mobject.py
smanim/mobject/text/__init__.py
smanim/mobject/text/fonts/Roboto/LICENSE.txt
smanim/mobject/text/fonts/Roboto/Roboto-Black.ttf
smanim/mobject/text/fonts/Roboto/Roboto-BlackItalic.ttf
smanim/mobject/text/fonts/Roboto/Roboto-Bold.ttf
smanim/mobject/text/fonts/Roboto/Roboto-BoldItalic.ttf
smanim/mobject/text/fonts/Roboto/Roboto-Italic.ttf
smanim/mobject/text/fonts/Roboto/Roboto-Light.ttf
smanim/mobject/text/fonts/Roboto/Roboto-LightItalic.ttf
smanim/mobject/text/fonts/Roboto/Roboto-Medium.ttf
smanim/mobject/text/fonts/Roboto/Roboto-MediumItalic.ttf
smanim/mobject/text/fonts/Roboto/Roboto-Regular.ttf
smanim/mobject/text/fonts/Roboto/Roboto-Thin.ttf
smanim/mobject/text/fonts/Roboto/Roboto-ThinItalic.ttf
smanim/mobject/text/fonts/computer-modern/SIL Open Font License.txt
smanim/mobject/text/fonts/computer-modern/cmunbi.ttf
smanim/mobject/text/fonts/computer-modern/cmunbl.ttf
smanim/mobject/text/fonts/computer-modern/cmunbmo.ttf
smanim/mobject/text/fonts/computer-modern/cmunbmr.ttf
smanim/mobject/text/fonts/computer-modern/cmunbso.ttf
smanim/mobject/text/fonts/computer-modern/cmunbsr.ttf
still_manim-0.1.1.dist-info/METADATA
still_manim-0.1.1.dist-info/WHEEL
still_manim-0.1.1.dist-info/RECORD
