Metadata-Version: 2.1
Name: still-manim
Version: 0.1.1
Summary: 
Author: tom11my
Author-email: tommy11jo@gmail.com
Requires-Python: >=3.10,<4.0
Classifier: Programming Language :: Python :: 3
Classifier: Programming Language :: Python :: 3.10
Classifier: Programming Language :: Python :: 3.11
Classifier: Programming Language :: Python :: 3.12
Requires-Dist: fonttools (>=4.50.0,<5.0.0)
Requires-Dist: networkx (>=3.2.1,<4.0.0)
Requires-Dist: numpy (>=1.26.4,<2.0.0)
Requires-Dist: pillow (>=10.0.0,<11.0.0)
Requires-Dist: svg-py (>=1.4.3,<2.0.0)
Requires-Dist: svgelements (>=1.9.6,<2.0.0)
Requires-Dist: typing-extensions (>=4.11.0,<5.0.0)
